airly/__init__.py
airly/_private.py
airly/exceptions.py
airly/installations.py
airly/measurements.py
airly-1.1.0.dist-info/LICENSE
airly-1.1.0.dist-info/METADATA
airly-1.1.0.dist-info/WHEEL
airly-1.1.0.dist-info/top_level.txt
airly-1.1.0.dist-info/RECORD
